reqease/__init__.py
reqease/data_classes.py
reqease/http_get.py
reqease/http_post.py
reqease/protocols.py
reqease/response_processor.py
reqease-0.1.3.dist-info/LICENSE
reqease-0.1.3.dist-info/METADATA
reqease-0.1.3.dist-info/WHEEL
reqease-0.1.3.dist-info/top_level.txt
reqease-0.1.3.dist-info/RECORD
